[
  {
    "title": "星球大战外传：侠盗一号",
    "href": "http://www.dytt8.net/html/gndy/dyzz/20170319/53514.html",
    "releaseTime": "2017-03-19",
    "decade": "2016",
    "nation": "美国",
    "specise": "动作/科幻/冒险",
    "language": "英语",
    "imdbScore": " 8.0/10 from 259,868 users",
    "runTime": "134分钟",
    "director": "加里斯·爱德华斯 Gareth Edwards",
    "imageUrl": "http://image18.poco.cn/mypoco/myphoto/20170319/22/185036732201703192212494122403851224_000.jpg"
  },
  {
    "title": "克里斯汀/绝望直播",
    "href": "http://www.dytt8.net/html/gndy/jddy/20170319/53513.html",
    "releaseTime": "2017-03-19",
    "decade": "2016",
    "nation": "美国",
    "specise": "剧情/传记",
    "language": "英语",
    "imdbScore": " 7.0/10 from 4,373 users",
    "runTime": "115分钟",
    "director": "Antonio Campos",
    "imageUrl": "http://image18.poco.cn/mypoco/myphoto/20170316/16/185036732201703161600341510170262817_002.jpg"
  },
  {
    "title": "爱国者之日",
    "href": "http://www.dytt8.net/html/gndy/dyzz/20170318/53507.html",
    "releaseTime": "2017-03-18",
    "decade": "2016",
    "nation": "美国",
    "specise": "剧情/历史/惊悚",
    "language": "英语",
    "imdbScore": " 7.5/10 from 18,196 users",
    "runTime": "133分钟",
    "director": "彼得·博格 Peter Berg",
    "imageUrl": "http://image18.poco.cn/mypoco/myphoto/20170315/14/185036732201703151453005231638774779_000.jpg"
  },
  {
    "title": "反攻/猎杀边境",
    "href": "http://www.dytt8.net/html/gndy/jddy/20170318/53506.html",
    "releaseTime": "2017-03-18",
    "decade": "2016",
    "nation": "美国",
    "specise": "动作/惊悚",
    "language": "英语",
    "imdbScore": " 5.4/10 from 1,527 users",
    "runTime": "107分钟",
    "director": "吉姆·格莱斯皮 Jim Gillespie",
    "imageUrl": "http://image18.poco.cn/mypoco/myphoto/20170316/16/185036732201703161600341510170262817_001.jpg"
  },
  {
    "title": "二十世纪女人",
    "href": "http://www.dytt8.net/html/gndy/dyzz/20170317/53492.html",
    "releaseTime": "2017-03-17",
    "decade": "2016",
    "nation": "美国",
    "specise": "剧情/喜剧",
    "language": "英语",
    "imdbScore": " 7.6/10 from 7,139 users",
    "runTime": "119分钟",
    "director": "迈克·米尔斯 Mike Mills",
    "imageUrl": "http://image18.poco.cn/mypoco/myphoto/20170316/16/185036732201703161600341510170262817_004.jpg"
  },
  {
    "title": "生化危机：终章",
    "href": "http://www.dytt8.net/html/gndy/dyzz/20170316/53482.html",
    "releaseTime": "2017-03-16",
    "decade": "2016",
    "nation": "美国",
    "specise": "动作/科幻/惊悚/恐怖",
    "language": "英语",
    "imdbScore": " 6.0/10 from 20,826 users",
    "runTime": "106分钟(美国)/99分钟(中国大陆)",
    "director": "保罗·安德森 Paul W.S. Anderson",
    "imageUrl": "http://image18.poco.cn/mypoco/myphoto/20170315/16/185036732201703151616351844522261475_001.jpg"
  },
  {
    "title": "黑夜传说5：血战",
    "href": "http://www.dytt8.net/html/gndy/dyzz/20170315/53481.html",
    "releaseTime": "2017-03-15",
    "decade": "2016",
    "nation": "美国",
    "specise": "动作/恐怖",
    "language": "英语",
    "imdbScore": " 6.2/10 from 15,375 users",
    "runTime": "91分钟",
    "director": "安娜·福斯特 Anna Foerster",
    "imageUrl": "http://image18.poco.cn/mypoco/myphoto/20170212/22/183365877201702122251403964815339311_000.jpg"
  },
  {
    "title": "爱国者之日",
    "href": "http://www.dytt8.net/html/gndy/jddy/20170315/53480.html",
    "releaseTime": "2017-03-15",
    "decade": "2016",
    "nation": "美国",
    "specise": "剧情/历史/惊悚",
    "language": "英语",
    "imdbScore": " 7.5/10 from 18,196 users",
    "runTime": "133分钟",
    "director": "彼得·博格 Peter Berg",
    "imageUrl": "http://image18.poco.cn/mypoco/myphoto/20170315/14/185036732201703151453005231638774779_000.jpg"
  },
  {
    "title": "刺客信条",
    "href": "http://www.dytt8.net/html/gndy/dyzz/20170314/53475.html",
    "releaseTime": "2017-03-14",
    "decade": "2016",
    "nation": "美国/英国/法国/香港",
    "specise": "动作/历史/科幻/冒险",
    "language": "英语/西班牙语",
    "imdbScore": " 6.2/10 from 64,416 users",
    "runTime": "116分钟",
    "director": "贾斯汀·库泽尔  Justin Kurzel",
    "imageUrl": "http://image18.poco.cn/mypoco/myphoto/20170310/22/185036732201703102220023586320669253_000.jpg"
  },
  {
    "title": "莫斯科陷落/异星引力",
    "href": "http://www.dytt8.net/html/gndy/jddy/20170314/53474.html",
    "releaseTime": "2017-03-14",
    "decade": "2017",
    "nation": "俄罗斯",
    "specise": "剧情/科幻",
    "language": "俄语",
    "imdbScore": " 5.6/10 from 1,085 users",
    "runTime": "133分钟",
    "director": "费奥多尔·邦达尔丘克 Fyodor Bondarchuk",
    "imageUrl": "http://image18.poco.cn/mypoco/myphoto/20170314/16/185036732201703141631213028651581411_000.jpg"
  },
  {
    "title": "斯隆女士/枪狂帝国",
    "href": "http://www.dytt8.net/html/gndy/dyzz/20170313/53466.html",
    "releaseTime": "2017-03-13",
    "decade": "2016",
    "nation": "美国/法国",
    "specise": "剧情/惊悚",
    "language": "英语",
    "imdbScore": " 6.6/10 from 5,352 users",
    "runTime": "132分钟",
    "director": "约翰·麦登 John Madden",
    "imageUrl": "http://image18.poco.cn/mypoco/myphoto/20170310/19/185036732201703101915002863258343209_000.jpg"
  },
  {
    "title": "心理医生/临床实验",
    "href": "http://www.dytt8.net/html/gndy/jddy/20170313/53465.html",
    "releaseTime": "2017-03-13",
    "decade": "2017",
    "nation": "美国",
    "specise": "惊悚",
    "language": "英语",
    "imdbScore": " 5.1/10 from 1,862 users",
    "runTime": "104分钟",
    "director": "Alistair Legrand",
    "imageUrl": "http://image18.poco.cn/mypoco/myphoto/20170311/22/185036732201703112223072053646553577_002.jpg"
  },
  {
    "title": "悍女",
    "href": "http://www.dytt8.net/html/gndy/jddy/20170312/53460.html",
    "releaseTime": "2017-03-12",
    "decade": "2016",
    "nation": "荷兰/法国",
    "specise": "西部/悬疑/惊悚",
    "language": "英语",
    "imdbScore": " 7.3/10 from 3,495 users",
    "runTime": "148分钟",
    "director": "马丁·寇霍文 Martin Koolhoven",
    "imageUrl": "http://image18.poco.cn/mypoco/myphoto/20170312/18/185036732201703121854334155221060590_001.jpg"
  },
  {
    "title": "绝望之室/鬼开门",
    "href": "http://www.dytt8.net/html/gndy/jddy/20170312/53459.html",
    "releaseTime": "2017-03-12",
    "decade": "2016",
    "nation": "美国",
    "specise": "剧情/惊悚/恐怖",
    "language": "英语",
    "imdbScore": " 3.9/10 from 3,477 users",
    "runTime": "85分钟",
    "director": "D·J·卡卢索 D.J. Caruso",
    "imageUrl": "http://image18.poco.cn/mypoco/myphoto/20170312/18/185036732201703121854334155221060590_000.jpg"
  },
  {
    "title": "那年夏天你去了哪里",
    "href": "http://www.dytt8.net/html/gndy/jddy/20170311/53454.html",
    "releaseTime": "2017-03-11",
    "decade": "2016",
    "nation": "中国/中国香港",
    "specise": "悬疑",
    "language": "普通话",
    "runTime": "89分钟",
    "director": "周隼 Chris Chow",
    "imageUrl": "http://image18.poco.cn/mypoco/myphoto/20170309/09/185036732201703090925212387164339853_001.jpg"
  },
  {
    "title": "猪猪侠之英雄猪少年",
    "href": "http://www.dytt8.net/html/gndy/jddy/20170311/53453.html",
    "releaseTime": "2017-03-11",
    "decade": "2017",
    "nation": "中国",
    "specise": "喜剧/动画/奇幻",
    "language": "普通话",
    "runTime": "91分钟",
    "director": "陆锦明 Jinming Lu / 钟裕 Yu Zhong",
    "imageUrl": "http://image18.poco.cn/mypoco/myphoto/20170311/22/185036732201703112223072053646553577_005.jpg"
  },
  {
    "title": "奇幻人形宠之甜心兔妹",
    "href": "http://www.dytt8.net/html/gndy/jddy/20170311/53452.html",
    "releaseTime": "2017-03-11",
    "decade": "2017",
    "nation": "中国",
    "specise": "喜剧/奇幻",
    "language": "普通话",
    "runTime": "1h 29mn",
    "director": "郝昭赫",
    "imageUrl": "http://image18.poco.cn/mypoco/myphoto/20170309/09/185036732201703090925212387164339853_000.jpg"
  },
  {
    "title": "刺客信条",
    "href": "http://www.dytt8.net/html/gndy/dyzz/20170310/53447.html",
    "releaseTime": "2017-03-10",
    "decade": "2016",
    "nation": "美国/英国/法国/香港",
    "specise": "动作/历史/科幻/冒险",
    "language": "英语/西班牙语",
    "imdbScore": " 6.2/10 from 64,416 users",
    "runTime": "116分钟",
    "director": "贾斯汀·库泽尔  Justin Kurzel",
    "imageUrl": "http://image18.poco.cn/mypoco/myphoto/20170310/22/185036732201703102220023586320669253_000.jpg"
  },
  {
    "title": "健忘村",
    "href": "http://www.dytt8.net/html/gndy/dyzz/20170310/53446.html",
    "releaseTime": "2017-03-10",
    "decade": "2017",
    "nation": "中国/中国台湾",
    "specise": "剧情/喜剧/奇幻/古装",
    "language": "普通话",
    "imdbScore": " 6.4/10 from 78 users",
    "runTime": "116分钟",
    "director": "陈玉勋 Yu-Hsun Chen",
    "imageUrl": "http://image18.poco.cn/mypoco/myphoto/20170310/19/185036732201703101915002863258343209_002.jpg"
  },
  {
    "title": "夜色人生",
    "href": "http://www.dytt8.net/html/gndy/dyzz/20170309/53441.html",
    "releaseTime": "2017-03-09",
    "decade": "2016",
    "nation": "美国",
    "specise": "剧情/犯罪",
    "language": "英语",
    "imdbScore": " 6.4/10 from 14,297 users",
    "runTime": "129分钟",
    "director": "本·阿弗莱克 Ben Affleck",
    "imageUrl": "http://image18.poco.cn/mypoco/myphoto/20170307/21/185036732201703072149021852868495956_000.jpg"
  },
  {
    "title": "恢复/索命APP",
    "href": "http://www.dytt8.net/html/gndy/jddy/20170309/53440.html",
    "releaseTime": "2017-03-09",
    "decade": "2016",
    "nation": "美国",
    "specise": "惊悚/恐怖",
    "language": "英语",
    "imdbScore": " 4.6/10 from 1,074 users",
    "runTime": "82分钟",
    "director": "Darrell Wheat",
    "imageUrl": "http://image18.poco.cn/mypoco/myphoto/20170309/22/185036732201703092231443792958682296_000.jpg"
  },
  {
    "title": "欢乐好声音",
    "href": "http://www.dytt8.net/html/gndy/dyzz/20170309/53434.html",
    "releaseTime": "2017-03-09",
    "decade": "2016",
    "nation": "美国",
    "specise": "喜剧/动画/歌舞",
    "language": "英语",
    "imdbScore": " 7.2/10 from 28,712 users",
    "runTime": "108分钟",
    "director": "加斯·詹宁斯 Garth Jennings / 克里斯托夫·卢尔德莱 Christophe Lourdelet",
    "imageUrl": "http://image18.poco.cn/mypoco/myphoto/20170308/07/6427623420170308073530076.jpg"
  },
  {
    "title": "我的诗篇",
    "href": "http://www.dytt8.net/html/gndy/dyzz/20170309/53433.html",
    "releaseTime": "2017-03-09",
    "decade": "2015",
    "nation": "中国",
    "specise": "纪录",
    "language": "普通话",
    "runTime": "104分钟",
    "director": "吴飞跃 Feiyue Wu / 秦晓宇 Xiaoyu Qin",
    "imageUrl": "http://image18.poco.cn/mypoco/myphoto/20170308/22/185036732201703082206146736129864646_000.jpg"
  },
  {
    "title": "爆头/突击死亡局",
    "href": "http://www.dytt8.net/html/gndy/jddy/20170307/53426.html",
    "releaseTime": "2017-03-07",
    "decade": "2016",
    "nation": "印度尼西亚",
    "specise": "动作/犯罪/惊悚",
    "language": "印尼语",
    "imdbScore": " 7.1/10 from 1,407 users",
    "runTime": "117分钟",
    "director": "提莫·塔哈亚托 Timo Tjahjanto / Kimo Stamboel",
    "imageUrl": "http://image18.poco.cn/mypoco/myphoto/20170306/18/185036732201703061822324427302865169_000.jpg"
  },
  {
    "title": "甜蜜蜜",
    "href": "http://www.dytt8.net/html/gndy/jddy/20170307/53425.html",
    "releaseTime": "2017-03-07",
    "decade": "1996",
    "nation": "香港",
    "specise": "剧情/爱情",
    "language": "粤语/普通话/英语",
    "imdbScore": " 8.2/10 from 3,251 users",
    "runTime": "116分钟",
    "director": "陈可辛 Peter Chan",
    "imageUrl": "http://image18.poco.cn/mypoco/myphoto/20170307/21/185036732201703072159051443361686186_000.jpg"
  },
  {
    "title": "假小子",
    "href": "http://www.dytt8.net/html/gndy/jddy/20170306/53415.html",
    "releaseTime": "2017-03-06",
    "decade": "2016",
    "nation": "美国/法国/加拿大",
    "specise": "动作/犯罪/惊悚",
    "language": "英语",
    "imdbScore": " 4.5/10 from 452 users",
    "runTime": "95分钟",
    "director": "沃尔特·希尔 Walter Hill",
    "imageUrl": "http://image18.poco.cn/mypoco/myphoto/20170306/18/185036732201703061822324427302865169_002.jpg"
  },
  {
    "title": "逃亡僵尸岛",
    "href": "http://www.dytt8.net/html/gndy/jddy/20170306/53414.html",
    "releaseTime": "2017-03-06",
    "decade": "2015",
    "nation": "英国",
    "specise": "科幻/恐怖",
    "language": "英语",
    "imdbScore": " 5.2/10 from 3,100 users",
    "runTime": "93分钟",
    "director": "史蒂夫·巴克 Steve Barker",
    "imageUrl": "http://image18.poco.cn/mypoco/myphoto/20170306/18/185036732201703061822324427302865169_001.jpg"
  },
  {
    "title": "你好，疯子",
    "href": "http://www.dytt8.net/html/gndy/dyzz/20170305/53401.html",
    "releaseTime": "2017-03-05",
    "decade": "2016",
    "nation": "中国",
    "specise": "剧情/惊悚/悬疑",
    "language": "普通话",
    "runTime": "107分钟",
    "director": "饶晓志 Xiaozhi Rao",
    "imageUrl": "http://image18.poco.cn/mypoco/myphoto/20170305/22/185036732201703052212198378850935504_000.jpg"
  },
  {
    "title": "威廉泽罗的重建",
    "href": "http://www.dytt8.net/html/gndy/jddy/20170305/53400.html",
    "releaseTime": "2017-03-05",
    "decade": "2014",
    "nation": "美国",
    "specise": "剧情/科幻/惊悚",
    "language": "英语",
    "imdbScore": " 5.4/10 from 686 users",
    "runTime": "98分钟",
    "director": "Dan Bush",
    "imageUrl": "http://image18.poco.cn/mypoco/myphoto/20160919/10/178343444201609191016563981787824274_000.jpg"
  }
]